romms_glaficplots/__init__.py
romms_glaficplots/plots.py
romms_glaficplots-0.0.29.dist-info/LICENSE.md
romms_glaficplots-0.0.29.dist-info/METADATA
romms_glaficplots-0.0.29.dist-info/WHEEL
romms_glaficplots-0.0.29.dist-info/top_level.txt
romms_glaficplots-0.0.29.dist-info/RECORD
