Metadata-Version: 2.1
Name: romms-glaficplots
Version: 0.0.29
Summary: A python package to make basic plots (errors and critical curves) for glafic
Home-page: https://github.com/romms921/romms_glaficplots.git
Author: Rommulus Lewis
Author-email: rommuluslewis@gmail.com
License: BSD 2-clause
Keywords: astronomy,astrophysics,gravitationallensing,lensing,glafic
Classifier: Development Status :: 1 - Planning
Classifier: Intended Audience :: Science/Research
Classifier: License :: OSI Approved :: BSD License
Classifier: Operating System :: POSIX :: Linux
Classifier: Programming Language :: Python :: 2
Classifier: Programming Language :: Python :: 2.7
Classifier: Programming Language :: Python :: 3
Classifier: Programming Language :: Python :: 3.4
Classifier: Programming Language :: Python :: 3.5
License-File: LICENSE.md
Requires-Dist: pandas
Requires-Dist: numpy
Requires-Dist: matplotlib
Requires-Dist: seaborn
